napari_dexp/__init__.py
napari_dexp/_reader.py
napari_dexp/_version.py
napari_dexp/_writer.py
napari_dexp/napari.yaml
napari_dexp/_tests/__init__.py
napari_dexp/_tests/test_io.py
napari_dexp-0.0.7.dist-info/LICENSE
napari_dexp-0.0.7.dist-info/METADATA
napari_dexp-0.0.7.dist-info/WHEEL
napari_dexp-0.0.7.dist-info/entry_points.txt
napari_dexp-0.0.7.dist-info/top_level.txt
napari_dexp-0.0.7.dist-info/RECORD
