Metadata-Version: 2.1
Name: napari-dexp
Version: 0.0.7
Summary: A simple plugin to use with napari
Home-page: https://github.com/royerlab/napari-dexp
Author: Jordao Bragantini
Author-email: jordao.bragantini@czbiohub.org
License: BSD-3
Classifier: Development Status :: 2 - Pre-Alpha
Classifier: Intended Audience :: Developers
Classifier: Framework :: napari
Classifier: Topic :: Software Development :: Testing
Classifier: Programming Language :: Python
Classifier: Programming Language :: Python :: 3
Classifier: Programming Language :: Python :: 3.7
Classifier: Programming Language :: Python :: 3.8
Classifier: Programming Language :: Python :: 3.9
Classifier: Operating System :: OS Independent
Classifier: License :: OSI Approved :: BSD License
Requires-Python: >=3.7
License-File: LICENSE
Requires-Dist: napari
Requires-Dist: napari-plugin-engine (>=0.1.4)
Requires-Dist: dexp
Requires-Dist: numpy
